vi_editor/__init__.py
vi_editor/main.py
vi_editor/assets/vi.ico
vi_editor-0.1.1.dist-info/licenses/LICENSE
vi_editor-0.1.1.dist-info/METADATA
vi_editor-0.1.1.dist-info/WHEEL
vi_editor-0.1.1.dist-info/entry_points.txt
vi_editor-0.1.1.dist-info/top_level.txt
vi_editor-0.1.1.dist-info/RECORD
