Metadata-Version: 2.4
Name: vi_editor
Version: 0.1.1
Summary: A simple Tkinter based VI editor
Author-email: Aditya Krishna Kotikalapudi <adityakkotikalapudi@gmail.com>
License: MIT
Project-URL: Homepage, https://github.com/AdityaKK0407/vi_editor
Project-URL: Source, https://github.com/AdityaKK0407/vi_editor
Requires-Python: >=3.10
License-File: LICENSE
Dynamic: license-file
